<?xml version="1.0" encoding="utf-8"?>
<!-- @author Великодный В.В. (Joonte Ltd.) -->
<XML>
<!-- *********************************************************************** -->
<!--
<Domain>/^([a-z0-9абвгдеёжзийклмнопрстуфхцчшщьыъэюя]([a-z0-9абвгдеёжзийклмнопрстуфхцчшщьыъэюя\-]*[a-z0-9абвгдеёжзийклмнопрстуфхцчшщьыъэюя])*\.)+[a-zрф]{2,4}$/ui</Domain>
<DomainName>/^[a-z0-9абвгдеёжзийклмнопрстуфхцчшщьыъэюя]([a-z0-9абвгдеёжзийклмнопрстуфхцчшщьыъэюя\-]*[a-z0-9абвгдеёжзийклмнопрстуфхцчшщьыъэюя])*$/ui</DomainName>

see: http://forum.lissyara.su/viewtopic.php?f=17&t=34580
-->
<Domain>/^([\d\pL]([\d\-\pL]*[\d\pL]){0,62}\.)+\pL{2,4}$/ui</Domain>
<DomainName>/^[\d\pL]([\d\-\pL]*[\d\pL]){2,62}$/ui</DomainName>
<!-- *********************************************************************** -->
<DnsDomain>/^([\d\pL]([\d\-\pL]*[\d\pL]){1,62}\.)+\pL{2,4}$/ui</DnsDomain>
<!-- *********************************************************************** -->
<!-- added by lissyara 2013-03-04 in 15:56 MSK for JBS-58 -->
<!-- .рф -->
<DomainName_xn--p1ai>/^[0-9а-я]([0-9а-я\-]*[0-9а-я])*$/ui</DomainName_xn--p1ai>
<!-- .ru -->
<DomainName_ru>/^[0-9a-z]([0-9a-z\-]*[0-9a-z])*$/ui</DomainName_ru>
<!-- *********************************************************************** -->
</XML>
